ranktools/__init__.py
ranktools/ranktools.py
ranktools-0.2.dist-info/LICENSE
ranktools-0.2.dist-info/METADATA
ranktools-0.2.dist-info/WHEEL
ranktools-0.2.dist-info/top_level.txt
ranktools-0.2.dist-info/RECORD
