Metadata-Version: 2.1
Name: ranktools
Version: 0.2
License-File: LICENSE
Requires-Dist: numpy >=1.15.0
